{
  "@context": {
    "dct" : "http://purl.org/dc/terms/",
    "dc": "http://purl.org/dc/elements/1.1/",
    "fedora" : "http://fedora.info/definitions/v4/repository#",
    "ebucore" : "http://www.ebu.ch/metadata/ontologies/ebucore/ebucore#",
    "schema": "http://schema.org/",
    "title" : {
      "@id": "dct:title"
    },
    "description" : {
      "@id": "dc:description"
    },
    "subjects" : {
      "@id": "dc:subject"
    },
    "creator" : {
      "@id": "dc:creator"
    },
    "creatorLink" : {
      "@id": "dct:creator",
      "@type" : "@id"
    },
    "createdBy" : {
      "@id": "fedora:createdBy"
    },
    "parent" : {
      "@id": "fedora:hasParent",
      "@type": "@id"
    },
    "isPartOf":{
      "@id" : "schema:isPartOf",
      "@type": "@id"
    },
    "mimeType" : {
      "@id" : "ebucore:hasMimeType"
    },
    "lastModified" : {
      "@type" : "http://www.w3.org/2001/XMLSchema#dateTime",
      "@id" : "fedora:lastModified"
    },
    "lastModifiedBy" : {
      "@id" : "fedora:lastModifiedBy"
    },
    "coverage" : {
      "@id" : "dc:coverage"
    },
    "subjectLinks" : {
      "@id" : "dct:subject",
      "@type" : "@id"
    },
    "publisher" : {
      "@id" : "dc:publisher"
    },
    "created" : {
      "@id" : "dct:created"
    },
    "type" : {
      "@id" : "dct:type"
    },
    "rightsLink" : {
      "@id" : "dct:rights",
      "@type" : "@id"
    }
  },
  "@explicit": true,
  "title": {
    "@default" : ""
  },
  "description": {
    "@default" : ""
  },
  "subjects": {
    "@default" : ""
  },
  "creator" : {
    "@default" : ""
  },
  "creatorLink" : {
    "@default" : ""
  },
  "createdBy" : {
    "@default" : ""
  },
  "isPartOf" : {
    "@default" : ""
  },
  "mimeType" : {
    "@default" : ""
  },
  "lastModified" : {
    "@default" : ""
  },
  "lastModifiedBy" : {
    "@default" : ""
  },
  "coverage" : {
    "@default" : ""
  },
  "subjectLinks" : {
    "@default" : ""
  },
  "publisher" : {
    "@default" : ""
  },
  "created" : {
    "@default" : ""
  },
  "type" : {
    "@default" : ""
  },
  "rightsLink" : {
    "@default" : ""
  }
}
